ripleyk/__init__.py
ripleyk/ripleyk.py
ripleyk-0.9.dist-info/licenses/LICENSE
ripleyk-0.9.dist-info/METADATA
ripleyk-0.9.dist-info/WHEEL
ripleyk-0.9.dist-info/top_level.txt
ripleyk-0.9.dist-info/RECORD
