Metadata-Version: 2.4
Name: ripleyk
Version: 0.9
Summary: Calculation of the Ripley K (spatial statistics) value in python
Home-page: https://github.com/SamPIngram/RipleyK
Author: Sam Ingram
Author-email: sp_ingram12@yahoo.co.uk
Classifier: Programming Language :: Python :: 3
Classifier: License :: OSI Approved :: MIT License
Classifier: Operating System :: OS Independent
Requires-Python: >=3.5
License-File: LICENSE
Requires-Dist: numpy>=1.19.2
Requires-Dist: scipy>=1.5.2
Dynamic: author
Dynamic: author-email
Dynamic: classifier
Dynamic: description
Dynamic: description-content-type
Dynamic: home-page
Dynamic: license-file
Dynamic: requires-dist
Dynamic: requires-python
Dynamic: summary
